Metadata-Version: 1.0
Name: GrilloModem
Version: 1.2.4
Summary: A small tool to easily send data (files, clipboard) between computers with 0 config, just using audio and mic.
Home-page: https://github.com/fisadev/grillo
Author: Juan Pedro Fisanotti
Author-email: fisadev@gmail.com
License: GPLv3
Keywords: audio,modem,clipboard,transfer
Platform: UNKNOWN
